numspy/__init__.py
numspy-1.0.dist-info/METADATA
numspy-1.0.dist-info/RECORD
numspy-1.0.dist-info/WHEEL
numspy-1.0.dist-info/top_level.txt
