Metadata-Version: 2.1
Name: numspy
Version: 1.0
Summary: A python module for sending free sms as well as finding details of a mobile Number via website way2sms.
Home-page: https://github.com/bhattsameer/numspy
Author: Debugger
Author-email: UNKNOWN
License: UNKNOWN
Keywords: Numspy Way2sms freesms futuresms sms numspy
Platform: UNKNOWN
Classifier: Intended Audience :: Developers
Classifier: Natural Language :: English
Classifier: Topic :: Communications
Classifier: License :: OSI Approved :: MIT License
Classifier: Programming Language :: Python
Classifier: Programming Language :: Python :: 3
Requires-Dist: beautifulsoup4
Requires-Dist: bs4
Requires-Dist: requests
Requires-Dist: huepy
